Workbook

Sheet Legend
A1: TopFarmer - Balance Sheet v0 (skeleton)
A2: Source of truth for every player-facing number. Game code must read exported CSVs, never hardcode values.
A5: HOW TO USE
A6: Blue text | B6: Hardcoded input. These are the cells you edit.
A7: Black text | B7: Formula. Do not edit - it will be overwritten by the next tuning pass.
A8: Green text | B8: Link to another tab.
A9: Yellow fill | B9: Key global lever. Changing these moves the whole economy.
A11: TABS
A12: Globals | B12: Economy-wide levers. Time multiplier, reward multiplier, price rules.
A13: Crops | B13: Every plantable crop. Derived gold/hr and xp/hr per plot = the difficulty curve.
A14: Goods | B14: Every produced ingredient and final good, with recipes and margins.
A15: Buildings | B15: Production buildings, costs, unlock levels, parallel slots.
A16: Progression | B16: Farm levels 1-10: XP curve, plots, storage, what unlocks.
A17: Orders | B17: Order rewards derived from the value of goods requested. Formula-driven, not hand-tuned.
A18: Currencies | B18: Gold and Starlight sources and sinks.
A20: SCOPE OF v0
B21: 3 crops, 2 production buildings, 10 levels. Deliberately rough.
B22: Spec called for 1 building; 2 are included so the Sunwheat > Flour > Bread chain is representable.
B23: Numbers here are placeholders chosen to be plausible, NOT tuned. Tuning is a separate roadmap phase.
A25: EXPORT RULE
B26: Each tab exports to /data/<tabname>.csv. Both this .xlsx and the CSVs are committed.
B27: Coder Agent never edits /data/ directly - it requests changes via progress.md.
A29: WORKED EXAMPLE
B30: First pass priced Flour at 14g. Input cost (3 Sunwheat @ 6g) was 18g, so milling DESTROYED 4g of value.
B31: Raw selling beat crafting - a trap the player would find before you did. Flour is now 24g. Check every margin after any price edit.
A33: TIME MODEL
B34: All durations are real-world seconds. Growth and production continue while the app is closed.

Sheet Globals
A1: Global Economy Levers
A2: Every time gate and reward rate in the game scales off these. Required by requirement E5 (monetization-readiness).
A4: Key | B4: Value | C4: Unit | D4: Notes
A5: GROWTH_TIME_MULT | B5: 1 | C5: multiplier | D5: Scales all crop growth durations. Lower = faster game. The primary pacing lever.
A6: PRODUCTION_TIME_MULT | B6: 1 | C6: multiplier | D6: Scales all building production durations.
A7: SELL_PRICE_MULT | B7: 1 | C7: multiplier | D7: Scales all sell prices. Use to inflate/deflate the economy without touching every row.
A8: XP_MULT | B8: 1 | C8: multiplier | D8: Scales all XP awards.
A9: ORDER_GOLD_MULT | B9: 1.6 | C9: multiplier | D9: Order gold reward = value of goods requested x this. Above 1.0 so orders beat raw selling.
A10: ORDER_XP_MULT | B10: 0.25 | C10: multiplier | D10: Order XP = goods value x this.
A11: TRAIN_BONUS_MULT | B11: 2.5 | C11: multiplier | D11: Large train/airship deliveries pay this instead of ORDER_GOLD_MULT.
A12: STARLIGHT_ORDER_CHANCE | B12: 0.15 | C12: probability | D12: Chance a completed standard order also awards 1 Starlight.
A13: STARLIGHT_HARVEST_CHANCE | B13: 0.01 | C13: probability | D13: Chance a harvest drops 1 Starlight.
A14: XP_CURVE_BASE | B14: 60 | C14: xp | D14: XP required for level 2. Feeds the Progression curve.
A15: XP_CURVE_EXP | B15: 1.85 | C15: exponent | D15: Level curve steepness. XP to reach level N = BASE x (N-1)^EXP.
A16: STARTING_GOLD | B16: 250 | C16: gold | D16: New save gold.
A17: STARTING_PLOTS | B17: 4 | C17: plots | D17: New save plot count.
A19: All values above are placeholders set by initial design, not derived from playtest data.

Sheet Crops
A1: Crops
A2: Gold/hr and XP/hr per plot are the real outputs here. Later crops should trend upward on both, but not monotonically - give the player a reason to keep growing early crops.
A4: id | B4: name | C4: unlock_level | D4: seed_cost | E4: growth_sec_base | F4: growth_sec_eff | G4: yield_qty | H4: sell_price_base | I4: sell_price_eff | J4: xp_base | K4: xp_eff | L4: revenue_per_harvest | M4: profit_per_harvest | N4: gold_per_hour | O4: xp_per_hour
A5: sunwheat | B5: Sunwheat | C5: 1 | D5: 3 | E5: 120 | F5: =E5*Globals!$B$5 -> 120 | G5: 2 | H5: 6 | I5: =H5*Globals!$B$7 -> 6 | J5: 2 | K5: =J5*Globals!$B$8 -> 2 | L5: =G5*I5 -> 12 | M5: =L5-D5 -> 9 | N5: =IFERROR(M5/(F5/3600),0) -> 270 | O5: =IFERROR(K5/(F5/3600),0) -> 60
A6: duskcorn | B6: Duskcorn | C6: 3 | D6: 12 | E6: 600 | F6: =E6*Globals!$B$5 -> 600 | G6: 2 | H6: 22 | I6: =H6*Globals!$B$7 -> 22 | J6: 6 | K6: =J6*Globals!$B$8 -> 6 | L6: =G6*I6 -> 44 | M6: =L6-D6 -> 32 | N6: =IFERROR(M6/(F6/3600),0) -> 192 | O6: =IFERROR(K6/(F6/3600),0) -> 36
A7: ember_pepper | B7: Ember Pepper | C7: 6 | D7: 40 | E7: 1800 | F7: =E7*Globals!$B$5 -> 1800 | G7: 3 | H7: 55 | I7: =H7*Globals!$B$7 -> 55 | J7: 16 | K7: =J7*Globals!$B$8 -> 16 | L7: =G7*I7 -> 165 | M7: =L7-D7 -> 125 | N7: =IFERROR(M7/(F7/3600),0) -> 250 | O7: =IFERROR(K7/(F7/3600),0) -> 32
A9: Placeholder values. sell_price_base is the design number; the game reads sell_price_eff.
A10: Rule of thumb to preserve when tuning: longer growth = higher gold/hr, so idle-friendly crops stay worth planting.

Sheet Goods
A1: Goods (ingredients and final goods)
A2: input_cost values inputs at their sell price - the opportunity cost of not selling them raw. margin below zero means the recipe destroys value.
A4: id | B4: name | C4: building_id | D4: unlock_level | E4: input1_id | F4: input1_qty | G4: input2_id | H4: input2_qty | I4: prod_sec_base | J4: prod_sec_eff | K4: output_qty | L4: sell_price_base | M4: sell_price_eff | N4: xp_base | O4: xp_eff | P4: input_cost | Q4: revenue | R4: margin | S4: gold_per_hour | T4: xp_per_hour
A5: flour | B5: Flour | C5: flourmill | D5: 2 | E5: sunwheat | F5: 3 | H5: 0 | I5: 300 | J5: =I5*Globals!$B$6 -> 300 | K5: 1 | L5: 24 | M5: =L5*Globals!$B$7 -> 24 | N5: 4 | O5: =N5*Globals!$B$8 -> 4 | P5: =IFERROR(IFERROR(INDEX(Crops!$I$5:$I$40,MATCH($E5,Crops!$A$5:$A$40,0)),INDEX($M$5:$M$40,MATCH($E5,$A$5:$A$40,0)))*$F5,0)+IFERROR(IFERROR(INDEX(Crops!$I$5:$I$40,MATCH($G5,Crops!$A$5:$A$40,0)),INDEX($M$5:$M$40,MATCH($G5,$A$5:$A$40,0)))*$H5,0) -> 18 | Q5: =K5*M5 -> 24 | R5: =Q5-P5 -> 6 | S5: =IFERROR(R5/(J5/3600),0) -> 72 | T5: =IFERROR(O5/(J5/3600),0) -> 48
A6: bread | B6: Bread | C6: bakery | D6: 4 | E6: flour | F6: 2 | H6: 0 | I6: 600 | J6: =I6*Globals!$B$6 -> 600 | K6: 1 | L6: 72 | M6: =L6*Globals!$B$7 -> 72 | N6: 12 | O6: =N6*Globals!$B$8 -> 12 | P6: =IFERROR(IFERROR(INDEX(Crops!$I$5:$I$40,MATCH($E6,Crops!$A$5:$A$40,0)),INDEX($M$5:$M$40,MATCH($E6,$A$5:$A$40,0)))*$F6,0)+IFERROR(IFERROR(INDEX(Crops!$I$5:$I$40,MATCH($G6,Crops!$A$5:$A$40,0)),INDEX($M$5:$M$40,MATCH($G6,$A$5:$A$40,0)))*$H6,0) -> 48 | Q6: =K6*M6 -> 72 | R6: =Q6-P6 -> 24 | S6: =IFERROR(R6/(J6/3600),0) -> 144 | T6: =IFERROR(O6/(J6/3600),0) -> 72
A7: ember_oil | B7: Ember Oil | C7: flourmill | D7: 7 | E7: ember_pepper | F7: 3 | H7: 0 | I7: 900 | J7: =I7*Globals!$B$6 -> 900 | K7: 1 | L7: 210 | M7: =L7*Globals!$B$7 -> 210 | N7: 30 | O7: =N7*Globals!$B$8 -> 30 | P7: =IFERROR(IFERROR(INDEX(Crops!$I$5:$I$40,MATCH($E7,Crops!$A$5:$A$40,0)),INDEX($M$5:$M$40,MATCH($E7,$A$5:$A$40,0)))*$F7,0)+IFERROR(IFERROR(INDEX(Crops!$I$5:$I$40,MATCH($G7,Crops!$A$5:$A$40,0)),INDEX($M$5:$M$40,MATCH($G7,$A$5:$A$40,0)))*$H7,0) -> 165 | Q7: =K7*M7 -> 210 | R7: =Q7-P7 -> 45 | S7: =IFERROR(R7/(J7/3600),0) -> 180 | T7: =IFERROR(O7/(J7/3600),0) -> 120
A8: spice_loaf | B8: Spice Loaf | C8: bakery | D8: 8 | E8: bread | F8: 1 | G8: ember_oil | H8: 1 | I8: 1200 | J8: =I8*Globals!$B$6 -> 1200 | K8: 1 | L8: 420 | M8: =L8*Globals!$B$7 -> 420 | N8: 48 | O8: =N8*Globals!$B$8 -> 48 | P8: =IFERROR(IFERROR(INDEX(Crops!$I$5:$I$40,MATCH($E8,Crops!$A$5:$A$40,0)),INDEX($M$5:$M$40,MATCH($E8,$A$5:$A$40,0)))*$F8,0)+IFERROR(IFERROR(INDEX(Crops!$I$5:$I$40,MATCH($G8,Crops!$A$5:$A$40,0)),INDEX($M$5:$M$40,MATCH($G8,$A$5:$A$40,0)))*$H8,0) -> 282 | Q8: =K8*M8 -> 420 | R8: =Q8-P8 -> 138 | S8: =IFERROR(R8/(J8/3600),0) -> 414 | T8: =IFERROR(O8/(J8/3600),0) -> 144
A10: Leave input2_id blank for single-input recipes. Lookups search Crops first, then Goods.
A11: Placeholder values. Every margin must stay positive or the crafting chain is a trap.

Sheet Buildings
A1: Production Buildings
A2: slots = how many jobs can run in parallel. A cheap early lever for both pacing and future monetization.
A4: id | B4: name | C4: unlock_level | D4: gold_cost | E4: build_sec | F4: slots | G4: notes
A5: flourmill | B5: Flourmill | C5: 2 | D5: 300 | E5: 300 | F5: 2 | G5: First production building. Unlocks the Sunwheat chain.
A6: bakery | B6: Bakery | C6: 4 | D6: 1200 | E6: 900 | F6: 2 | G6: Second tier. Consumes Flour.
A8: Additional slots per building are a natural later paid upgrade (requirement E5). Keep slots data-driven.

Sheet Progression
A1: Farm Levels 1-10
A2: XP to reach level N = XP_CURVE_BASE x (N-1)^XP_CURVE_EXP. Change the curve in Globals, not here.
A4: level | B4: xp_to_reach | C4: cumulative_xp | D4: plots_unlocked | E4: storage_cap | F4: unlocks
A5: 1 | B5: 0 | C5: 0 | D5: =Globals!$B$17+INT((A5-1)*1.5) -> 4 | E5: =50+(A5-1)*25 -> 50 | F5: Sunwheat. Starting plots.
A6: 2 | B6: =ROUND(Globals!$B$14*(A6-1)^Globals!$B$15,0) -> 60 | C6: =C5+B6 -> 60 | D6: =Globals!$B$17+INT((A6-1)*1.5) -> 5 | E6: =50+(A6-1)*25 -> 75 | F6: Flourmill. Flour.
A7: 3 | B7: =ROUND(Globals!$B$14*(A7-1)^Globals!$B$15,0) -> 216 | C7: =C6+B7 -> 276 | D7: =Globals!$B$17+INT((A7-1)*1.5) -> 7 | E7: =50+(A7-1)*25 -> 100 | F7: Duskcorn. Order board.
A8: 4 | B8: =ROUND(Globals!$B$14*(A8-1)^Globals!$B$15,0) -> 458 | C8: =C7+B8 -> 734 | D8: =Globals!$B$17+INT((A8-1)*1.5) -> 8 | E8: =50+(A8-1)*25 -> 125 | F8: Bakery. Bread.
A9: 5 | B9: =ROUND(Globals!$B$14*(A9-1)^Globals!$B$15,0) -> 780 | C9: =C8+B9 -> 1514 | D9: =Globals!$B$17+INT((A9-1)*1.5) -> 10 | E9: =50+(A9-1)*25 -> 150 | F9: Territory expansion I. Decor storage.
A10: 6 | B10: =ROUND(Globals!$B$14*(A10-1)^Globals!$B$15,0) -> 1178 | C10: =C9+B10 -> 2692 | D10: =Globals!$B$17+INT((A10-1)*1.5) -> 11 | E10: =50+(A10-1)*25 -> 175 | F10: Ember Pepper. Pets.
A11: 7 | B11: =ROUND(Globals!$B$14*(A11-1)^Globals!$B$15,0) -> 1651 | C11: =C10+B11 -> 4343 | D11: =Globals!$B$17+INT((A11-1)*1.5) -> 13 | E11: =50+(A11-1)*25 -> 200 | F11: Ember Oil. Daily quests.
A12: 8 | B12: =ROUND(Globals!$B$14*(A12-1)^Globals!$B$15,0) -> 2196 | C12: =C11+B12 -> 6539 | D12: =Globals!$B$17+INT((A12-1)*1.5) -> 14 | E12: =50+(A12-1)*25 -> 225 | F12: Spice Loaf. Train deliveries.
A13: 9 | B13: =ROUND(Globals!$B$14*(A13-1)^Globals!$B$15,0) -> 2811 | C13: =C12+B13 -> 9350 | D13: =Globals!$B$17+INT((A13-1)*1.5) -> 16 | E13: =50+(A13-1)*25 -> 250 | F13: Territory expansion II.
A14: 10 | B14: =ROUND(Globals!$B$14*(A14-1)^Globals!$B$15,0) -> 3495 | C14: =C13+B14 -> 12845 | D14: =Globals!$B$17+INT((A14-1)*1.5) -> 17 | E14: =50+(A14-1)*25 -> 275 | F14: Weekly quests. Layout saving.
A16: plots and storage_cap use placeholder formulas, not design intent. Replace with a considered curve in the tuning phase.

Sheet Orders
A1: Orders and Deliveries
A2: Rewards are derived from the value of what is requested. Never hand-write a gold reward - it guarantees drift.
A4: order_id | B4: type | C4: min_level | D4: item1_id | E4: qty1 | F4: item2_id | G4: qty2 | H4: item3_id | I4: qty3 | J4: goods_value | K4: gold_reward | L4: xp_reward | M4: starlight_reward
A5: ORD_S_01 | B5: standard | C5: 3 | D5: sunwheat | E5: 8 | G5: 0 | I5: 0 | J5: =IFERROR(IFERROR(INDEX(Crops!$I$5:$I$40,MATCH($D5,Crops!$A$5:$A$40,0)),INDEX(Goods!$M$5:$M$40,MATCH($D5,Goods!$A$5:$A$40,0)))*$E5,0)+IFERROR(IFERROR(INDEX(Crops!$I$5:$I$40,MATCH($F5,Crops!$A$5:$A$40,0)),INDEX(Goods!$M$5:$M$40,MATCH($F5,Goods!$A$5:$A$40,0)))*$G5,0)+IFERROR(IFERROR(INDEX(Crops!$I$5:$I$40,MATCH($H5,Crops!$A$5:$A$40,0)),INDEX(Goods!$M$5:$M$40,MATCH($H5,Goods!$A$5:$A$40,0)))*$I5,0) -> 48 | K5: =ROUND(J5*IF($B5="train",Globals!$B$11,Globals!$B$9),0) -> 77 | L5: =ROUND(J5*Globals!$B$10,0) -> 12 | M5: =IF($B5="train",2,0) -> 0
A6: ORD_S_02 | B6: standard | C6: 4 | D6: flour | E6: 4 | F6: sunwheat | G6: 6 | I6: 0 | J6: =IFERROR(IFERROR(INDEX(Crops!$I$5:$I$40,MATCH($D6,Crops!$A$5:$A$40,0)),INDEX(Goods!$M$5:$M$40,MATCH($D6,Goods!$A$5:$A$40,0)))*$E6,0)+IFERROR(IFERROR(INDEX(Crops!$I$5:$I$40,MATCH($F6,Crops!$A$5:$A$40,0)),INDEX(Goods!$M$5:$M$40,MATCH($F6,Goods!$A$5:$A$40,0)))*$G6,0)+IFERROR(IFERROR(INDEX(Crops!$I$5:$I$40,MATCH($H6,Crops!$A$5:$A$40,0)),INDEX(Goods!$M$5:$M$40,MATCH($H6,Goods!$A$5:$A$40,0)))*$I6,0) -> 132 | K6: =ROUND(J6*IF($B6="train",Globals!$B$11,Globals!$B$9),0) -> 211 | L6: =ROUND(J6*Globals!$B$10,0) -> 33 | M6: =IF($B6="train",2,0) -> 0
A7: ORD_S_03 | B7: standard | C7: 5 | D7: bread | E7: 3 | F7: flour | G7: 2 | I7: 0 | J7: =IFERROR(IFERROR(INDEX(Crops!$I$5:$I$40,MATCH($D7,Crops!$A$5:$A$40,0)),INDEX(Goods!$M$5:$M$40,MATCH($D7,Goods!$A$5:$A$40,0)))*$E7,0)+IFERROR(IFERROR(INDEX(Crops!$I$5:$I$40,MATCH($F7,Crops!$A$5:$A$40,0)),INDEX(Goods!$M$5:$M$40,MATCH($F7,Goods!$A$5:$A$40,0)))*$G7,0)+IFERROR(IFERROR(INDEX(Crops!$I$5:$I$40,MATCH($H7,Crops!$A$5:$A$40,0)),INDEX(Goods!$M$5:$M$40,MATCH($H7,Goods!$A$5:$A$40,0)))*$I7,0) -> 264 | K7: =ROUND(J7*IF($B7="train",Globals!$B$11,Globals!$B$9),0) -> 422 | L7: =ROUND(J7*Globals!$B$10,0) -> 66 | M7: =IF($B7="train",2,0) -> 0
A8: ORD_T_01 | B8: train | C8: 8 | D8: bread | E8: 10 | F8: ember_oil | G8: 4 | H8: spice_loaf | I8: 2 | J8: =IFERROR(IFERROR(INDEX(Crops!$I$5:$I$40,MATCH($D8,Crops!$A$5:$A$40,0)),INDEX(Goods!$M$5:$M$40,MATCH($D8,Goods!$A$5:$A$40,0)))*$E8,0)+IFERROR(IFERROR(INDEX(Crops!$I$5:$I$40,MATCH($F8,Crops!$A$5:$A$40,0)),INDEX(Goods!$M$5:$M$40,MATCH($F8,Goods!$A$5:$A$40,0)))*$G8,0)+IFERROR(IFERROR(INDEX(Crops!$I$5:$I$40,MATCH($H8,Crops!$A$5:$A$40,0)),INDEX(Goods!$M$5:$M$40,MATCH($H8,Goods!$A$5:$A$40,0)))*$I8,0) -> 2400 | K8: =ROUND(J8*IF($B8="train",Globals!$B$11,Globals!$B$9),0) -> 6000 | L8: =ROUND(J8*Globals!$B$10,0) -> 600 | M8: =IF($B8="train",2,0) -> 2
A10: These four are format examples. Live orders should be generated at runtime from unlocked items using these same formulas.
A11: Standard orders award Starlight probabilistically (Globals STARLIGHT_ORDER_CHANCE); train orders award it deterministically.

Sheet Currencies
A1: Currencies
A2: Gold is the working currency. Starlight is scarce and must always have more demand than supply.
A4: currency | B4: flow | C4: source_or_sink | D4: amount | E4: notes
A5: gold | B5: source | C5: Selling crops | D5: see Crops | E5: Baseline income. Deliberately the worst gold/hr option.
A6: gold | B6: source | C6: Selling goods | D6: see Goods | E6: Better than raw crops after accounting for time.
A7: gold | B7: source | C7: Standard orders | D7: value x ORDER_GOLD_MULT | E7: Best routine income. Drives engagement with the order board.
A8: gold | B8: source | C8: Train deliveries | D8: value x TRAIN_BONUS_MULT | E8: Large, infrequent, long completion window.
A9: gold | B9: sink | C9: Seeds | D9: see Crops | E9: Small continuous drain.
A10: gold | B10: sink | C10: Buildings | D10: see Buildings | E10: Major early sink.
A11: gold | B11: sink | C11: Territory expansion | D11: TBD | E11: Should be the dominant mid-game sink. Not yet specified.
A12: gold | B12: sink | C12: Decor | D12: TBD | E12: Optional sink. Needed or late-game gold becomes meaningless.
A13: starlight | B13: source | C13: Order completion | D13: 1 @ 15% chance | E13: Globals STARLIGHT_ORDER_CHANCE.
A14: starlight | B14: source | C14: Harvest drop | D14: 1 @ 1% chance | E14: Globals STARLIGHT_HARVEST_CHANCE.
A15: starlight | B15: source | C15: Train delivery | D15: 2 guaranteed | E15: The reliable path. Rewards planning.
... A18: starlight | B18: sink | C18: Storage upgrade | D18: TBD | E18: Same.
A20: TBD rows are unresolved design questions, not omissions. They must be closed before the tuning phase.
